insurance_predict_mcp/__init__.py
insurance_predict_mcp/server.py
insurance_predict_mcp/models/lightgbm.pkl
insurance_predict_mcp-1.1.0.dist-info/METADATA
insurance_predict_mcp-1.1.0.dist-info/WHEEL
insurance_predict_mcp-1.1.0.dist-info/entry_points.txt
insurance_predict_mcp-1.1.0.dist-info/top_level.txt
insurance_predict_mcp-1.1.0.dist-info/RECORD
