Metadata-Version: 2.4
Name: insurance-predict-mcp
Version: 1.1.0
Summary: LightGBM Insurance Premium Prediction MCP Server
Author: Insurance Team
Keywords: mcp,fastmcp,lightgbm,insurance,prediction
Classifier: Development Status :: 4 - Beta
Classifier: Intended Audience :: Developers
Classifier: Programming Language :: Python :: 3
Classifier: Programming Language :: Python :: 3.10
Classifier: Programming Language :: Python :: 3.11
Classifier: Programming Language :: Python :: 3.12
Classifier: Programming Language :: Python :: 3.13
Requires-Python: >=3.10
Requires-Dist: fastmcp>=2.12.0
Requires-Dist: joblib>=1.4.0
Requires-Dist: numpy>=2.1.0
Requires-Dist: lightgbm>=4.5.0
Requires-Dist: scikit-learn>=1.0.0
Requires-Dist: matplotlib>=3.10.7
Requires-Dist: graphviz>=0.21
Provides-Extra: dev
Requires-Dist: pytest>=7.0; extra == "dev"
Requires-Dist: pytest-asyncio>=0.21.0; extra == "dev"
